Metadata-Version: 2.1
Name: joker-masquerade
Version: 0.0.2
Summary: highly experimental security tools
Home-page: https://github.com/frozflame/joker-masquerade
Author: frozflame
Author-email: frozflame@outlook.com
License: GNU General Public License (GPL)
Platform: UNKNOWN
Classifier: Programming Language :: Python
Classifier: Programming Language :: Python :: 3
Classifier: Programming Language :: Python :: 3.4
Classifier: Programming Language :: Python :: 3.5
Classifier: Programming Language :: Python :: 3.6
Classifier: Programming Language :: Python :: 3.7
Classifier: Programming Language :: Python :: 3.8
Classifier: Programming Language :: Python :: 3.9
Classifier: Programming Language :: Python :: 3.10
License-File: LICENSE
